tileviewer
