Metadata-Version: 1.0
Name: tileviewer
Version: 0.1.1
Summary: UNKNOWN
Home-page: UNKNOWN
Author: Brett Graham
Author-email: braingram720@gmail.com
License: UNKNOWN
Platform: UNKNOWN
